{
    "en": {
      "name": "Name",
      "description": "Description",
      "video_url": "Video URL(YouTube)",
      "set": "Sets",
      "repetition": "Reps",
      "duration": "Duration",
      "weight": "Weight",
      "rpe": "RPE",
      "close": "Close",
      "exercisehistory": "Exercise history",
      "sets": "Sets",
      "reps": "Reps",
      "weight": "Weight",
      "RECENT": "RECENT",
      "ExerciseComplete": "Exercise Complete!",
      "Duration": "Duration",
      "Sets": "Sets",
      "Reps": "Reps",
      "Weight": "Weight",
      "RPE": "RPE",
      "Rating": "Rating",
      "Save": "SAVE",
      "min": "min",
      "profileinformation": "Profile information",
      "FriendCode": "FriendCode",
      "Name": "Name",
      "Age": "Age",
      "Sex": "Sex",
      "Weight": "Weight",
      "Height": "Height",
      "ProfileVisibility": "ProfileVisibility",
      "Profile": "Profile",
      "Workout": "Workout settings",
      "workoutMeasurment": "Weight measurement",
      "smallestPlate": "Smallest plate",
      "save": "Save",
      "profile": "Profile",
      "addfriend": "Add friend",
      "frienderror": "You can't add yourself as a friend!",
      "search": "Searching for: ",
      "alrfriend": "You already have a friend request from this user! Accepting the request...",
      "friendrequest": "Friend request accepted!",
      "alrfriend2": "You are already friends with this user!",
      "friendrequest2": "Friend request already sent!",
      "friendsent": "Friend request sent!",
      "monday": "Monday",
      "tuesday": "Tuesday",
      "wednesday": "Wednesday",
      "thursday": "Thursday",
      "friday": "Friday",
      "saturday": "Saturday",
      "sunday": "Sunday",
      "newWorkout": "NEW WORKOUT",
      "workoutName": "Workout name",
      "cancel": "Cancel",
      "planbuilder": "PLAN BUILDER",
      "new": "NEW",
      "workout": "WORKOUT",
      "previousWorkouts": "Previous Workouts",
      "date": "Date",
      "rating": "Rating",
      "rpe": "RPE",
      "duration": "Duration",
      "time": "mins",
      "start": "START",
      "stop": "STOP",
      "currentexercise": "Current exercise",
      "nextexercise": "Next exercise",
      "currentexerciseduration": "Current exercise duration",
      "min": "min",
      "sec": "s",
      "seeworkout": "Click to see full workout",
      "exercise": "Exercise",
      "sets": "Sets",
      "reps": "Reps",
      "name": "NAME",
      "close": "Close",
      "add": "Add",
      "addw": "Add workout",
      "squat": "Squat",
      "benchpress": "Bench Press",
      "deadlift": "Deadlift",
      "pullups": "Pull-Ups",
      "plank": "Plank",
      "GotoPlanBuilder": "Go to Plan Builder",
      "togglechat": "Toggle Chat",
      "newExercise": "New Exercise",
      "addE": "Add Exercise",
      "chatbot": "Hi, I am fitbot by closedAI. How can I help you?",
      "returnMain": "Return to main Page",
      "typemessage": "Type a message...",
      "private": "Private",
      "public": "Public",
      "selectlanguage": "Select Language",
      "turkish": "Turkish",
      "russian": "Russian",
      "english": "English",
      "WorkoutComplete": "Workout Complete!",
      "workoutName": "Workout name",
      "date": "Date",
      "duration": "Duration",
      "logOut": "Log Out",
      "gobackQue": "Go back to questionnaire",
      "backtoMain": "Back to main page",
      "tagss": "Submit Tags",
      "Tag": "Tags",
      "cancel":"Cancel"
    
    },
    "tr": {
        "name": "İsim",
        "description": "Açıklama",
        "video_url": "Video URL(YouTube)",
        "set": "Setler",
        "repetition": "Tekrarlar",
        "duration": "Süre",
        "weight": "Ağırlık",
        "rpe": "RPE",
        "close": "Kapat",
        "exercisehistory": "Egzersiz geçmişi",
        "sets": "Setler",
        "reps": "Tekrarlar",
        "weight": "Ağırlık",
        "RECENT": "SON",
        "ExerciseComplete": "Egzersiz Tamamlandı!",
        "Duration": "Süre",
        "Sets": "Setler",
        "Reps": "Tekrarlar",
        "Weight": "Ağırlık",
        "RPE": "RPE",
        "Rating": "Değerlendirme",
        "Save": "KAYDET",
        "min": "dakika",
        "profileinformation": "Profil bilgileri",
        "FriendCode": "Arkadaş Kodu",
        "Name": "Isim",
        "Age": "Yaş",
        "Sex": "Cinsiyet",
        "Weight": "Kilo",
        "Height": "Boy",
        "ProfileVisibility": "Profil Gizliliği",
        "Profile": "Profil",
        "Workout": "Antrenman ayarları",
        "workoutMeasurment": "Ağırlık ölçümü",
        "smallestPlate": "En küçük plaka",
        "save": "Kaydet",
        "profile": "Profil",
        "addfriend": "Arkadaş ekle",
        "frienderror": "Kendini arkadaş olarak ekleyemezsin!",
        "search": "Aranıyor: ",
        "alrfriend": "Bu kullanıcıdan zaten arkadaşlık isteğiniz var! İsteği kabul ediyorum...",
        "friendrequest": "Arkadaşlık isteği kabul edildi!",
        "alrfriend2": "Bu kullanıcıyla zaten arkadaşsınız!",
        "friendrequest2": "Arkadaşlık isteği zaten gönderildi!",
        "friendsent": "Arkadaşlık isteği gönderildi!",
        "monday": "Pazartesi",
        "tuesday": "Salı",
        "wednesday": "Çarşamba",
        "thursday": "Perşembe",
        "friday":"Cuma",
        "saturday": "Cumartesi",
        "sunday": "Pazar",
        "newWorkout": "YENİ ANTRENMAN",
        "workoutName": "Antrenman adı",
        "cancel": "İptal",
        "planbuilder": "PLAN OLUŞTURUCU",
        "new": "YENİ",
        "workout": "ANTRENMAN",
        "previousWorkouts": "Önceki Antrenmanlar",
        "date": "Tarih",
        "rating": "Değerlendirme",
        "rpe": "RPE",
        "duration": "Süre",
        "time": "dakika",
        "start": "BAŞLA",
        "stop": "DUR",
        "currentexercise": "Mevcut egzersiz",
        "nextexercise": "Sonraki egzersiz",
        "currentexerciseduration": "Mevcut egzersiz süresi",
        "min": "dk",
        "sec": "sn",
        "seeworkout": "Tam antrenmanı görmek için tıklayın",
        "exercise": "Egzersiz",
        "sets": "Setler",
        "reps": "Tekrarlar",
        "name": "İSİM",
        "close": "Kapat",
        "add": "Ekle",
        "addw": "Antrenman ekle",
        "squat": "Çömelme",
        "benchpress": "Bench Press",
        "deadlift": "Deadlift",
        "pullups": "Çekme",
        "plank": "Plank",
        "GotoPlanBuilder": "Plan Oluşturucuya Git",
        "togglechat": "Sohbeti Aç/Kapat",
        "newExercise": "Yeni Egzersiz",
        "addE": "Egzersiz Ekle",
        "chatbot": "Merhaba, ben fitbot. Nasıl yardımcı olabilirim?",
        "returnMain": "Ana Sayfaya Dön",
        "typemessage": "Bir mesaj yazın...",
        "private": "Özel",
        "public": "Genel",
        "selectlanguage": "Dil Seçiniz",
        "turkish": "Türkçe",
        "russian": "Rusça",
        "english": "İngilizce",
        "WorkoutComplete": "Antrenman Tamamlandı!",
        "workoutName": "Antrenman adı",
        "date": "Tarih",
        "duration": "Süre",
        "logOut": "Çıkış Yap",
        "gobackQue": "Anket'e geri dön",
        "backtoMain": "Ana sayfaya dön",
        "tagss": "Etiketleri Gönder",
        "Tag": "Etiketler",
        "cancel":"İptal"



    },
    "ru": {
            "name": "Имя",
            "description": "Описание",
            "video_url": "Видео URL(YouTube)",
            "set": "Наборы",
            "repetition": "Повторы",
            "duration": "Продолжительность",
            "weight": "Вес",
            "rpe": "RPE",
            "close": "Закрыть",
            "exercisehistory": "История упражнений",
            "sets": "Наборы",
            "reps": "Повторы",
            "weight": "Вес",
            "RECENT": "ПОСЛЕДНИЕ",
            "ExerciseComplete": "Упражнение завершено!",
            "Duration": "Продолжительность",
            "Sets": "Наборы",
            "Reps": "Повторы",
            "Weight": "Вес",
            "RPE": "RPE",
            "Rating": "Рейтинг",
            "Save": "СОХРАНИТЬ",
            "min": "минут",
            "profileinformation": "Информация профиля",
            "FriendCode": "Код друга",
            "Name": "Имя",
            "Age": "Возраст",
            "Sex": "Пол",
            "Weight": "Вес",
            "Height": "Рост",
            "ProfileVisibility": "Видимость профиля",
            "Profile": "Профиль",
            "Workout": "Настройки тренировки",
            "workoutMeasurment": "Измерение веса",
            "smallestPlate": "Самая маленькая гиря",
            "save": "Сохранить",
            "profile": "Профиль",
            "addfriend": "Добавить друга",
            "frienderror": "Вы не можете добавить себя в друзья!",
            "search": "Поиск: ",
            "alrfriend": "У вас уже есть запрос на дружбу от этого пользователя! Принимаю запрос...",
            "friendrequest": "Запрос на дружбу принят!",
            "alrfriend2": "Вы уже дружите с этим пользователем!",
            "friendrequest2": "Запрос на дружбу уже отправлен!",
            "friendsent": "Запрос на дружбу отправлен!",
            "monday": "Понедельник",
            "tuesday": "Вторник",
            "wednesday": "Среда",
            "thursday": "Четверг",
            "friday": "Пятница",
            "saturday": "Суббота",
            "sunday": "Воскресенье",
            "newWorkout": "НОВАЯ ТРЕНИРОВКА",
            "workoutName": "Название тренировки",
            "cancel": "Отмена",
            "planbuilder": "ПЛАНИРОВЩИК",
            "new": "НОВАЯ",
            "workout": "ТРЕНИРОВКА",
            "previousWorkouts": "Предыдущие тренировки",
            "date": "Дата",
            "rating": "Рейтинг",
            "rpe": "RPE",
            "duration": "Продолжительность",
            "time": "минут",
            "start": "НАЧАТЬ",
            "stop": "СТОП",
            "currentexercise": "Текущее упражнение",
            "nextexercise": "Следующее упражнение",
            "currentexerciseduration":   "Продолжительность текущего упражнения",
            "min": "мин",
            "sec": "сек",
            "seeworkout": "Нажмите, чтобы увидеть полную тренировку",
            "exercise": "Упражнение",
            "sets": "Подходы",
            "reps": "Повторы",
            "name": "ИМЯ",
            "close": "Закрыть",
            "add": "Добавить",
            "addw": "Добавить тренировку",
            "squat": "Приседания",
            "benchpress": "Жим лежа",
            "deadlift": "Становая тяга",
            "pullups": "Подтягивания",
            "plank": "Планка",
            "GotoPlanBuilder": "Перейти к планировщику",
            "togglechat": "Переключить чат",
            "newExercise": "Новое упражнение",
            "addE": "Добавить упражнение",
            "chatbot": "Привет, я fitbot. Чем могу помочь?",
            "returnMain": "Назад",
            "typemessage": "Введите сообщение...",
            "private": "Приватный",
            "public": "Публичный",
            "selectlanguage": "Выберите язык",
            "turkish": "Турецкий",
            "russian": "Русский",
            "english": "Английский",
            "WorkoutComplete": "Тренировка завершена!",
            "workoutName": "Название тренировки",
            "date": "Дата",
            "duration": "Продолжительность",
            "logOut": "Выйти",
            "gobackQue": "К опроснику",
            "backtoMain": "Назад",
            "tagss": "Отправить теги",
            "Tag": "Теги",
            "cancel":"Отмена"

     }
}